md2hwpx/MarkdownToHtml.py
md2hwpx/MarkdownToHwpx.py
md2hwpx/__init__.py
md2hwpx/__main__.py
md2hwpx/blank.hwpx
md2hwpx/cli.py
md2hwpx/config.py
md2hwpx/converter_api.py
md2hwpx/exceptions.py
md2hwpx/frontmatter_parser.py
md2hwpx/marko_adapter.py
md2hwpx-0.1.0.dist-info/licenses/LICENSE
md2hwpx-0.1.0.dist-info/licenses/NOTICE
md2hwpx-0.1.0.dist-info/METADATA
md2hwpx-0.1.0.dist-info/WHEEL
md2hwpx-0.1.0.dist-info/entry_points.txt
md2hwpx-0.1.0.dist-info/top_level.txt
md2hwpx-0.1.0.dist-info/RECORD
