Metadata-Version: 2.4
Name: md2hwpx
Version: 0.1.0
Summary: Convert Markdown to HWPX (Korean Hancom Office format)
Home-page: https://github.com/msjang/md2hwpx
Author: md2hwpx Contributors
License: MIT
Project-URL: Source, https://github.com/msjang/md2hwpx
Project-URL: Tracker, https://github.com/msjang/md2hwpx/issues
Project-URL: Fork of, https://github.com/msjang/pypandoc-hwpx
Classifier: Programming Language :: Python :: 3
Classifier: License :: OSI Approved :: MIT License
Classifier: Operating System :: OS Independent
Requires-Python: >=3.9
License-File: LICENSE
License-File: NOTICE
Requires-Dist: marko>=2.0.0
Requires-Dist: python-frontmatter>=1.0.0
Requires-Dist: Pillow
Dynamic: author
Dynamic: classifier
Dynamic: description
Dynamic: description-content-type
Dynamic: home-page
Dynamic: license
Dynamic: license-file
Dynamic: project-url
Dynamic: requires-dist
Dynamic: requires-python
Dynamic: summary
